auto_dotenv.py
hatch_autorun_pyauto_dotenv.pth
pyauto_dotenv-0.1.0.dist-info/METADATA
pyauto_dotenv-0.1.0.dist-info/WHEEL
pyauto_dotenv-0.1.0.dist-info/licenses/LICENSE
pyauto_dotenv-0.1.0.dist-info/RECORD
