Metadata-Version: 2.1
Name: pyauto-dotenv
Version: 0.1.0
Summary: Automatically load .env variables if auto-dotenv is installed
Project-URL: Repository, https://github.com/hmiladhia/auto-dotenv
Project-URL: Issues, https://github.com/hmiladhia/auto-dotenv/issues
Author-email: Dhia Hmila <dhiahmila.dev@gmail.com>
Maintainer-email: Dhia Hmila <dhiahmila.dev@gmail.com>
License: MIT License
License-File: LICENSE
Keywords: configurations,dotenv,env,environment variables,secrets
Classifier: Development Status :: 5 - Production/Stable
Classifier: License :: OSI Approved :: MIT License
Classifier: Operating System :: OS Independent
Classifier: Programming Language :: Python :: 3
Requires-Python: >=3.8
Requires-Dist: python-dotenv>=1.0.1
